Metadata-Version: 2.4
Name: python-socketio-rishavrmoney
Version: 4.6.1
Summary: Socket.IO server
Home-page: http://github.com/miguelgrinberg/python-socketio/
Author: Miguel Grinberg
Author-email: miguelgrinberg50@gmail.com
License: MIT
Platform: any
Classifier: Environment :: Web Environment
Classifier: Intended Audience :: Developers
Classifier: License :: OSI Approved :: MIT License
Classifier: Operating System :: OS Independent
Classifier: Programming Language :: Python
Classifier: Programming Language :: Python :: 2
Classifier: Programming Language :: Python :: 3
Classifier: Topic :: Internet :: WWW/HTTP :: Dynamic Content
Classifier: Topic :: Software Development :: Libraries :: Python Modules
License-File: LICENSE
Requires-Dist: six>=1.9.0
Requires-Dist: python-engineio<4,>=3.13.0
Provides-Extra: client
Requires-Dist: requests>=2.21.0; extra == "client"
Requires-Dist: websocket-client>=0.54.0; extra == "client"
Provides-Extra: asyncio-client
Requires-Dist: aiohttp>=3.4; extra == "asyncio-client"
Requires-Dist: websockets>=7.0; extra == "asyncio-client"
Dynamic: author
Dynamic: author-email
Dynamic: classifier
Dynamic: description
Dynamic: home-page
Dynamic: license
Dynamic: license-file
Dynamic: platform
Dynamic: provides-extra
Dynamic: requires-dist
Dynamic: summary
